{
	"aggregate_function_based_on": "",
	"color": "#D97706",
	"creation": "2026-02-20 00:00:00.000000",
	"currency": "",
	"doctype": "Number Card",
	"document_type": "Purchase Order",
	"dynamic_filters_json": "[]",
	"filters_json": "[[\"Purchase Order\",\"status\",\"not in\",[\"Completed\",\"Cancelled\"]]]",
	"function": "Count",
	"is_public": 1,
	"is_standard": 1,
	"label": "Open Purchase Orders",
	"modified": "2026-02-20 00:00:00.000000",
	"modified_by": "Administrator",
	"module": "NexPort",
	"name": "Open Purchase Orders",
	"owner": "Administrator",
	"parent_document_type": "",
	"report_function": "Count",
	"show_percentage_stats": 0,
	"stats_time_interval": "Monthly",
	"type": "Document Type",
	"unit": ""
}
